hexiliary/__init__.py
hexiliary/application.py
hexiliary-0.0.3.dist-info/LICENSE.md
hexiliary-0.0.3.dist-info/METADATA
hexiliary-0.0.3.dist-info/WHEEL
hexiliary-0.0.3.dist-info/RECORD
