Metadata-Version: 2.1
Name: hexiliary
Version: 0.0.3
Summary: 
License: Apache-2.0
Author: Denis Ivlev
Author-email: di-erz@yandex.ru
Requires-Python: >=3.12,<4.0
Classifier: License :: OSI Approved :: Apache Software License
Classifier: Programming Language :: Python :: 3
Classifier: Programming Language :: Python :: 3.12
